itptit/__init__.py
itptit/common/__init__.py
itptit/common/_stdout.py
itptit/common/exceptions.py
itptit/common/math/__init__.py
itptit/common/math/math.py
itptit/common/math/math.pyi
itptit/common/random/__init__.py
itptit/common/random/random.py
itptit/common/random/random.pyi
itptit/generator/__init__.py
itptit/generator/_base.py
itptit/generator/input.py
itptit/generator/input.pyi
itptit/generator/output.py
itptit/generator/output.pyi
itptit/judge/__init__.py
itptit/judge/_common.py
itptit/judge/_thread.py
itptit/judge/judge.py
itptit/judge/judge.pyi
itptit-1.0.2.dist-info/LICENSE
itptit-1.0.2.dist-info/METADATA
itptit-1.0.2.dist-info/WHEEL
itptit-1.0.2.dist-info/top_level.txt
itptit-1.0.2.dist-info/RECORD
