Metadata-Version: 2.1
Name: itptit
Version: 1.0.2
Summary: Python library of IT Club PTIT HN
Home-page: https://github.com/hlighT-git/itptit
Author: Hlight
Author-email: hlight.mail@gmail.com
License: MIT
Classifier: Programming Language :: Python :: 3
Classifier: Operating System :: OS Independent
License-File: LICENSE
